{
  "3argoIKnoiDFGW4sxTqThn": {
    "p": 38,
    "d": 272352
  },
  "4qbeQEmxBKVkmDvuWm7xcx": {
    "p": 35,
    "d": 206362
  },
  "5uDyfB2SPeNGoP3UtcYxjd": {
    "p": 25,
    "d": 253546
  },
  "4L3iQPsLnNn6anGcGV2H3V": {
    "p": 19,
    "d": 64574
  },
  "75dsvIpsSwympxsQCMTZmr": {
    "p": 34,
    "d": 210291
  },
  "5QIRBSqO4tHdlmL0lOoYqq": {
    "p": 26,
    "d": 233973
  },
  "5qfIKhePQ7q6kq0x60zqrF": {
    "p": 17,
    "d": 168927
  },
  "3YgxYmqnb4gPHhWCa6Ecup": {
    "p": 46,
    "d": 329795
  },
  "4IAIe2ehYOp4TaCbSARv7t": {
    "p": 43,
    "d": 219026
  },
  "4spkZ6gRKh827yp6JI6TN1": {
    "p": 64,
    "d": 211666
  },
  "3NgpON25NdYTOS4w8LVJTi": {
    "p": 49,
    "d": 248680
  },
  "2Fn8rz8L3mhOIK4P4puebE": {
    "p": 25,
    "d": 239773
  },
  "51kAIhfkRBjzdKDQeVqxHT": {
    "p": 36,
    "d": 242800
  },
  "0JEh6Sbo5KWE7Lq4dDRigF": {
    "p": 30,
    "d": 275957
  },
  "2qPLHVvmDtH4bfDJYE7PbK": {
    "p": 19,
    "d": 153619
  },
  "7xsnPgblD5D2L1ozGpkRD7": {
    "p": 19,
    "d": 183792
  },
  "5yDNXXhHijNWh75k5udqcj": {
    "p": 27,
    "d": 190226
  },
  "0vnj14R32mrC6hHcSD5ANT": {
    "p": 49,
    "d": 199160
  },
  "5UjlsxSVj5wIrgWk20d6e7": {
    "p": 7,
    "d": 164080
  },
  "6DGl9TtxYTpMFrmZa1mwEz": {
    "p": 59,
    "d": 184304
  },
  "5LMw1XCB3cGJx6TRHaXaEr": {
    "p": 22,
    "d": 224483
  },
  "1jA0gxVATJituaoIAPgt5B": {
    "p": 31,
    "d": 178653
  },
  "1Lq5ApqhIWUXzlryFX2K6J": {
    "p": 69,
    "d": 206211
  },
  "3bN5O5WRbA9yEvBzAudLgC": {
    "p": 51,
    "d": 249626
  },
  "7bwLvVHpxOuOtg50aicp7c": {
    "p": 51,
    "d": 174000
  },
  "4nvfu7TOV9D1xIPaiN2F4a": {
    "p": 41,
    "d": 210560
  },
  "2Q7shjIV6gP2VHqosVlDMd": {
    "p": 50,
    "d": 239416
  },
  "1gsxREaPi4uaTL4OWYKaak": {
    "p": 21,
    "d": 179680
  },
  "4HEDd8FxRsIPUMiVmbhACc": {
    "p": 26,
    "d": 258403
  },
  "4sBoX30at6PzZNGSGY1cin": {
    "p": 42,
    "d": 214460
  },
  "24DQVStZgV2sjIy56NuWmd": {
    "p": 7,
    "d": 187500
  },
  "0IfTkYdVPl4R72T8vLKxrp": {
    "p": 53,
    "d": 226586
  },
  "74rLJAuf5StVGiwqL5UPDe": {
    "p": 27,
    "d": 259552
  },
  "5DelwP5vBag1H1Nmlygcu8": {
    "p": 56,
    "d": 242627
  },
  "2tfE60fbixm6m6GWN2dPA3": {
    "p": 25,
    "d": 274886
  },
  "6bItLRYluXP1XP3MtlsGR4": {
    "p": 15,
    "d": 312502
  },
  "5zQQvypqjcSb0ul1ncqSns": {
    "p": 50,
    "d": 261377
  },
  "62Nf5JMXvh8yGjkPYTTMO0": {
    "p": 26,
    "d": 273554
  },
  "1hLuavqY2dkoOmgMOxD47P": {
    "p": 6,
    "d": 265691
  },
  "0WqV5GdMdsp72XYKWw2QuH": {
    "p": 37,
    "d": 230093
  },
  "1BwV1AuCzF9SW1C5fPTzOU": {
    "p": 42,
    "d": 204040
  },
  "0oN2SeYGbHIlGKvKfzrpLR": {
    "p": 53,
    "d": 215426
  },
  "2wXLAFYIclP6NfmmugFAuL": {
    "p": 57,
    "d": 209506
  },
  "4vVsdSD5jwTotE5lMkrC8i": {
    "p": 39,
    "d": 212000
  },
  "3GajQYxCIJSygFreSPDhMx": {
    "p": 3,
    "d": 154686
  }
}